autotoloka/__init__.py
autotoloka/create_pool.py
autotoloka/create_task.py
autotoloka/handler.py
autotoloka/json_data.py
autotoloka/pipeline.py
autotoloka/test.py
autotoloka/utils.py
autotoloka/json_files/collecting_images.json
autotoloka/json_files/validating_segmentation.json
autotoloka-0.0.20.dist-info/METADATA
autotoloka-0.0.20.dist-info/WHEEL
autotoloka-0.0.20.dist-info/top_level.txt
autotoloka-0.0.20.dist-info/RECORD
